README.md
setup.py
latinexpr/__init__.py
python_latin_expr_fr.egg-info/PKG-INFO
python_latin_expr_fr.egg-info/SOURCES.txt
python_latin_expr_fr.egg-info/dependency_links.txt
python_latin_expr_fr.egg-info/not-zip-safe
python_latin_expr_fr.egg-info/top_level.txt