Metadata-Version: 1.0
Name: python-latin-expr-fr
Version: 0.1.2
Summary: Random Latin expression with French translations to upgrade your brain !
Home-page: https://github.com/remaudcorentin-dev/python-latin-expr-fr
Author: Corentin Remaud
Author-email: remaudcorentin.dev@gmail.com
License: MIT
Platform: UNKNOWN
